with_argparse/__init__.py
with_argparse/configure_argparse.py
with_argparse/disable_argparse.py
with_argparse/impl.py
with_argparse/test.py
with_argparse/types.py
with_argparse/utils.py
with_argparse-1.0.4.dist-info/licenses/LICENSE
with_argparse-1.0.4.dist-info/METADATA
with_argparse-1.0.4.dist-info/WHEEL
with_argparse-1.0.4.dist-info/top_level.txt
with_argparse-1.0.4.dist-info/RECORD
