Metadata-Version: 2.4
Name: with-argparse
Version: 1.0.4
Summary: A simple but handy Python library to generate a `argparse.ArgumentParser` object from a type-annotated method 
Author-email: Moritz Hennen <mail@fleance.de>
License: Apache 2.0
Project-URL: repository, https://github.com/fleonce/with-argparse/
Keywords: argparse,type annotation,auto
Classifier: Development Status :: 3 - Alpha
Classifier: Intended Audience :: Developers
Classifier: Intended Audience :: Science/Research
Classifier: Intended Audience :: System Administrators
Classifier: Topic :: Scientific/Engineering :: Artificial Intelligence
Classifier: Topic :: Utilities
Classifier: License :: OSI Approved :: Apache Software License
Classifier: Natural Language :: English
Classifier: Programming Language :: Python :: 3 :: Only
Requires-Python: >=3.8
License-File: LICENSE
Dynamic: license-file
